merkify
