Metadata-Version: 1.1
Name: Merkify
Version: 0.1.0
Summary: Simple Merkle Tree implementation
Home-page: https://github.com/user/reponame
Author: Bani Singh
Author-email: banihns@gmail.com
License: MIT
Download-URL: https://github.com/banisingh/Merkify/archive/0.1.0.tar.gz
Keywords: merkletree,bitcoin,binarytree
Platform: UNKNOWN
Classifier: Development Status :: 3 - Alpha
Classifier: Intended Audience :: Developers
Classifier: Topic :: Software Development :: Build Tools
Classifier: License :: OSI Approved :: MIT License
Classifier: Operating System :: OS Independent
Classifier: Programming Language :: Python :: 3
Classifier: Programming Language :: Python :: 3.4
Classifier: Programming Language :: Python :: 3.5
Classifier: Programming Language :: Python :: 3.6
Classifier: Programming Language :: Python :: 3.7
